metro/__init__.py
metro/admin.py
metro/apps.py
metro/models.py
metro/tasks.py
metro/tests.py
metro/locale/ru/LC_MESSAGES/django.mo
metro/locale/ru/LC_MESSAGES/django.po
metro/management/__init__.py
metro/management/commands/__init__.py
metro/management/commands/clear_metro.py
metro/management/commands/load_metro.py
metro/migrations/0001_initial.py
metro/migrations/0002_auto_20181009_1427.py
metro/migrations/__init__.py
metro/parser/__init__.py
metro/parser/base.py
metro/parser/providers/__init__.py
metro/parser/providers/ekat.py
metro/parser/providers/kazan.py
metro/parser/providers/kiev.py
metro/parser/providers/london.py
metro/parser/providers/minsk.py
metro/parser/providers/moscow.py
metro/parser/providers/novgorod.py
metro/parser/providers/novosib.py
metro/parser/providers/omsk.py
metro/parser/providers/samara.py
metro/parser/providers/spb.py
metro/parser/providers/tokyo.py
django_metro-0.4.5.dist-info/LICENSE
django_metro-0.4.5.dist-info/METADATA
django_metro-0.4.5.dist-info/WHEEL
django_metro-0.4.5.dist-info/top_level.txt
django_metro-0.4.5.dist-info/zip-safe
django_metro-0.4.5.dist-info/RECORD
