Metadata-Version: 2.1
Name: django-metro
Version: 0.4.5
Summary: Basic metro models for Django 1.7+,     plus the parser that fills models with actual data     (lines numbers, lines titles, lines colors, the names     of the lines, the station names) from various data     sources (primary - Wikipedia).
Home-page: https://github.com/xfenix/django-metro
Author: Denis Anikin
Author-email: ad@xfenix.ru
License: UNKNOWN
Platform: UNKNOWN
Classifier: Development Status :: 4 - Beta
Classifier: Environment :: Web Environment
Classifier: Framework :: Django
Classifier: Intended Audience :: Developers
Classifier: Operating System :: OS Independent
Classifier: Programming Language :: Python
Classifier: Programming Language :: Python :: 2
Classifier: Programming Language :: Python :: 2.6
Classifier: Programming Language :: Python :: 2.7
Classifier: Programming Language :: Python :: 3
Requires-Dist: Django (==2.1.2)
Requires-Dist: BeautifulSoup4
Requires-Dist: requests
Requires-Dist: six
